{"commitInfo":{"version":1,"timestamp":1657906379795,"userId":"trino","userName":"trino","operation":"WRITE","operationParameters":{"queryId":"20220715_173258_00005_7ihpw"},"clusterId":"trino-390-trino-coordinator","readVersion":0,"isolationLevel":"WriteSerializable","blindAppend":true}}
{"add":{"path":"20220715_173258_00005_7ihpw-e936cda3-59b0-4bd9-82e1-816157fee88a","partitionValues":{},"size":306,"modificationTime":1657906379529,"dataChange":true,"stats":"{\"numRecords\":2,\"minValues\":{\"name\":\"Jane\",\"id\":1},\"maxValues\":{\"name\":\"John\",\"id\":2},\"nullCount\":{\"name\":0,\"id\":0}}","tags":{}}}
